setup.py
bin/tailcolor
bin/tailflash
bin/tailrain
tailcolor/__init__.py
tailcolor/tailcolor.py
tailcolor.egg-info/PKG-INFO
tailcolor.egg-info/SOURCES.txt
tailcolor.egg-info/dependency_links.txt
tailcolor.egg-info/not-zip-safe
tailcolor.egg-info/requires.txt
tailcolor.egg-info/top_level.txt