Metadata-Version: 1.0
Name: tailcolor
Version: 0.2.3
Summary: 'tail -F' with color feedback based on how recent the line was seen
Home-page: https://github.com/bVector/tailcolor
Author: bVector
Author-email: b@bvector.net
License: MIT
Platform: UNKNOWN
